feedforge/__init__.py
feedforge/analysis.py
feedforge/cli.py
feedforge/core.py
feedforge/server.py
feedforge-0.2.8.dist-info/licenses/LICENSE
feedforge-0.2.8.dist-info/METADATA
feedforge-0.2.8.dist-info/WHEEL
feedforge-0.2.8.dist-info/entry_points.txt
feedforge-0.2.8.dist-info/top_level.txt
feedforge-0.2.8.dist-info/RECORD
