Metadata-Version: 2.4
Name: feedforge
Version: 0.2.8
Summary: A powerful AI-driven tool to customize your YouTube feed based on your content preferences using browser automation
Author-email: Rishabh Bhandari <rishabhbhandari6@gmail.com>
License-Expression: MIT
Project-URL: Homepage, https://github.com/RishabhKodes/feedforge
Project-URL: Repository, https://github.com/RishabhKodes/feedforge
Project-URL: Documentation, https://github.com/RishabhKodes/feedforge#readme
Project-URL: Bug Tracker, https://github.com/RishabhKodes/feedforge/issues
Keywords: youtube,feed,automation,ai,browser,selenium,recommendations,pipx
Classifier: Development Status :: 4 - Beta
Classifier: Intended Audience :: End Users/Desktop
Classifier: Operating System :: OS Independent
Classifier: Programming Language :: Python :: 3
Classifier: Programming Language :: Python :: 3.9
Classifier: Programming Language :: Python :: 3.10
Classifier: Programming Language :: Python :: 3.11
Classifier: Programming Language :: Python :: 3.12
Classifier: Topic :: Internet :: WWW/HTTP :: Browsers
Classifier: Topic :: Multimedia :: Video
Classifier: Topic :: Software Development :: Libraries :: Python Modules
Classifier: Environment :: Console
Requires-Python: >=3.9
License-File: LICENSE
Requires-Dist: langchain-openai>=0.0.5
Requires-Dist: google-api-python-client>=2.0.0
Requires-Dist: click>=8.0.0
Requires-Dist: python-dotenv>=1.0.0
Requires-Dist: selenium>=4.0.0
Requires-Dist: geckodriver-autoinstaller>=0.1.0
Requires-Dist: chromedriver-autoinstaller>=0.6.0
Requires-Dist: openai>=1.0.0
Requires-Dist: fastapi>=0.112.0
Requires-Dist: uvicorn>=0.30.0
Requires-Dist: httpx>=0.27.0
Requires-Dist: pydantic>=2.7.0
Dynamic: license-file
